test_packaging/__init__.py
test_packaging/utils.py
test_packaging_dkt_test-0.1.0.dist-info/METADATA
test_packaging_dkt_test-0.1.0.dist-info/WHEEL
test_packaging_dkt_test-0.1.0.dist-info/top_level.txt
test_packaging_dkt_test-0.1.0.dist-info/RECORD
