Metadata-Version: 2.4
Name: test-packaging-dkt-test
Version: 0.1.0
Summary: Add your description here
Requires-Python: >=3.11
Requires-Dist: pandas>=2.3.1
Requires-Dist: scikit-learn>=1.7.1
